micro/Micro.py
micro/__init__.py
micro/_imports_.py
micro/metadata.json
micro/micro.min.js
micro/micro.min.js.map
micro/package-info.json
micro/css/micro.css
dash_micro-0.0.1.dist-info/LICENSE
dash_micro-0.0.1.dist-info/METADATA
dash_micro-0.0.1.dist-info/WHEEL
dash_micro-0.0.1.dist-info/top_level.txt
dash_micro-0.0.1.dist-info/RECORD
