Metadata-Version: 2.1
Name: dash-micro
Version: 0.0.1
Summary: React microphone component for dash
Author: TBone Behr <teresabehr@gmail.com>
License: MIT
Classifier: Framework :: Dash
License-File: LICENSE
